beluga/__init__.py
beluga/helpers.py
beluga/metrics.py
beluga_ml-1.1.0.dist-info/LICENSE
beluga_ml-1.1.0.dist-info/METADATA
beluga_ml-1.1.0.dist-info/WHEEL
beluga_ml-1.1.0.dist-info/top_level.txt
beluga_ml-1.1.0.dist-info/RECORD
