Metadata-Version: 2.1
Name: beluga-ml
Version: 1.1.0
Summary: A Python library to help make your Machine Learning easier
Home-page: https://github.com/datasciencewithdaniel/beluga
Author: Data Science with Daniel
License: GPL-3.0
Platform: UNKNOWN
License-File: LICENSE
Requires-Dist: numpy
